odoo/addons/hr_expense_analytic_distribution/README.rst
odoo/addons/hr_expense_analytic_distribution/__init__.py
odoo/addons/hr_expense_analytic_distribution/__manifest__.py
odoo/addons/hr_expense_analytic_distribution/i18n/hr_expense_analytic_distribution.pot
odoo/addons/hr_expense_analytic_distribution/models/__init__.py
odoo/addons/hr_expense_analytic_distribution/models/hr_expense.py
odoo/addons/hr_expense_analytic_distribution/models/hr_expense_distribution.py
odoo/addons/hr_expense_analytic_distribution/models/hr_expense_sheet.py
odoo/addons/hr_expense_analytic_distribution/readme/CONTRIBUTORS.rst
odoo/addons/hr_expense_analytic_distribution/readme/DESCRIPTION.rst
odoo/addons/hr_expense_analytic_distribution/readme/USAGE.rst
odoo/addons/hr_expense_analytic_distribution/security/ir.model.access.csv
odoo/addons/hr_expense_analytic_distribution/static/description/icon.png
odoo/addons/hr_expense_analytic_distribution/static/description/index.html
odoo/addons/hr_expense_analytic_distribution/tests/__init__.py
odoo/addons/hr_expense_analytic_distribution/tests/test_expense.py
odoo/addons/hr_expense_analytic_distribution/views/hr_expense_distribution_views.xml
odoo/addons/hr_expense_analytic_distribution/views/hr_expense_sheet_views.xml
odoo14_addon_hr_expense_analytic_distribution-14.0.1.0.1.dist-info/METADATA
odoo14_addon_hr_expense_analytic_distribution-14.0.1.0.1.dist-info/WHEEL
odoo14_addon_hr_expense_analytic_distribution-14.0.1.0.1.dist-info/top_level.txt
odoo14_addon_hr_expense_analytic_distribution-14.0.1.0.1.dist-info/RECORD
